shadecrypt/__init__.py
shadecrypt/cli.py
shadecrypt/config.py
shadecrypt/core.py
shadecrypt/exceptions.py
shadecrypt/schedule.py
shadecrypt/service.py
shadecrypt-0.1.dist-info/METADATA
shadecrypt-0.1.dist-info/WHEEL
shadecrypt-0.1.dist-info/entry_points.txt
shadecrypt-0.1.dist-info/top_level.txt
shadecrypt-0.1.dist-info/RECORD
