Metadata-Version: 2.4
Name: shadecrypt
Version: 0.1
Summary: A class oriented lightweight database with a cli wrapper for any device: store, update, copy, and remove structured data with a single command. Perfect for embedded devices, mobiles, devtools, and quick local services.
Author: Shade
Author-email: adesolasherifdeen3@gmail.com
License: GPL-3.0
Project-URL: GitHub, https://github.com/harkerbyte
Project-URL: Facebook, https://facebook.com/harkerbyte
Project-URL: Whatsapp, https://whatsapp.com/channel/0029Vb5f98Z90x2p6S1rhT0S
Project-URL: Youtube, https://youtube.com/@harkerbyte
Project-URL: Instagram, https://instagram.com/harkerbyte
Classifier: Programming Language :: Python :: 3
Classifier: License :: OSI Approved :: MIT License
Classifier: Environment :: Console
Classifier: Intended Audience :: Developers
Classifier: Topic :: Database :: Database Engines/Servers
Requires-Python: >=3.8
Dynamic: author
Dynamic: author-email
Dynamic: classifier
Dynamic: description
Dynamic: description-content-type
Dynamic: license
Dynamic: project-url
Dynamic: requires-python
Dynamic: summary
